odoo/addons/sale_commission/README.rst
odoo/addons/sale_commission/__init__.py
odoo/addons/sale_commission/__manifest__.py
odoo/addons/sale_commission/i18n/es.po
odoo/addons/sale_commission/i18n/it.po
odoo/addons/sale_commission/i18n/ja.po
odoo/addons/sale_commission/i18n/pt_BR.po
odoo/addons/sale_commission/i18n/sale_commission.pot
odoo/addons/sale_commission/i18n/tr.po
odoo/addons/sale_commission/models/__init__.py
odoo/addons/sale_commission/models/sale_order.py
odoo/addons/sale_commission/readme/CONTRIBUTORS.md
odoo/addons/sale_commission/readme/DESCRIPTION.md
odoo/addons/sale_commission/readme/USAGE.md
odoo/addons/sale_commission/security/ir.model.access.csv
odoo/addons/sale_commission/static/description/icon.png
odoo/addons/sale_commission/static/description/icon.svg
odoo/addons/sale_commission/static/description/index.html
odoo/addons/sale_commission/tests/__init__.py
odoo/addons/sale_commission/tests/test_sale_commission.py
odoo/addons/sale_commission/views/sale_order_view.xml
odoo_addon_sale_commission-17.0.1.1.0.3.dist-info/METADATA
odoo_addon_sale_commission-17.0.1.1.0.3.dist-info/WHEEL
odoo_addon_sale_commission-17.0.1.1.0.3.dist-info/top_level.txt
odoo_addon_sale_commission-17.0.1.1.0.3.dist-info/RECORD
